telnetlib3/__init__.py
telnetlib3/accessories.py
telnetlib3/client.py
telnetlib3/client_base.py
telnetlib3/client_shell.py
telnetlib3/conio.py
telnetlib3/dns.py
telnetlib3/relay_server.py
telnetlib3/server.py
telnetlib3/server_base.py
telnetlib3/server_shell.py
telnetlib3/slc.py
telnetlib3/stream_reader.py
telnetlib3/stream_writer.py
telnetlib3/telnetlib.py
telnetlib3/telopt.py
telnetlib3/telsh.py
telnetlib3/contrib/__init__.py
telnetlib3/contrib/cp437.py
telnetlib3/contrib/wcwidth.py
telnetlib3-2.0.7.dist-info/licenses/LICENSE.txt
telnetlib3-2.0.7.dist-info/METADATA
telnetlib3-2.0.7.dist-info/WHEEL
telnetlib3-2.0.7.dist-info/entry_points.txt
telnetlib3-2.0.7.dist-info/top_level.txt
telnetlib3-2.0.7.dist-info/zip-safe
telnetlib3-2.0.7.dist-info/RECORD
