Metadata-Version: 2.4
Name: telnetlib3
Version: 2.0.7
Summary: Python 3 asyncio Telnet server and client Protocol library
Home-page: http://telnetlib3.rtfd.org/
Author: Jeff Quast
Author-email: contact@jeffquast.com
License: ISC
Keywords: telnet,server,client,bbs,mud,utf8,cp437,api,library,asyncio,talker
Platform: any
Classifier: License :: OSI Approved :: ISC License (ISCL)
Classifier: Programming Language :: Python :: 3.7
Classifier: Programming Language :: Python :: 3.8
Classifier: Programming Language :: Python :: 3.9
Classifier: Programming Language :: Python :: 3.10
Classifier: Programming Language :: Python :: 3.11
Classifier: Programming Language :: Python :: 3.12
Classifier: Programming Language :: Python :: 3.13
Classifier: Intended Audience :: Developers
Classifier: Development Status :: 4 - Beta
Classifier: Topic :: System :: Networking
Classifier: Topic :: Terminals :: Telnet
Classifier: Topic :: System :: Shells
Classifier: Topic :: Internet
Requires-Python: >=3.7
License-File: LICENSE.txt
Dynamic: author
Dynamic: author-email
Dynamic: classifier
Dynamic: description
Dynamic: home-page
Dynamic: keywords
Dynamic: license
Dynamic: license-file
Dynamic: platform
Dynamic: requires-python
Dynamic: summary
